{"data": [{"Tags": ["Item", "Creature"], "Genus": "m", "Word": "банан"}, {"Tags": ["Creature"], "Genus": "m", "Word": "негр"}, {"Tags": ["Item"], "Genus": "m", "Word": "меч"}, {"Tags": ["Creature"], "Genus": "f", "Word": "колесница"}, {"Tags": ["Item", "Location"], "Genus": "m", "Word": "шрам"}, {"Tags": ["Item"], "Genus": "m", "Word": "ботинок"}, {"Tags": ["Creature"], "Genus": "m", "Word": "лазарь"}, {"Tags": ["Creature", "Item"], "Genus": "m", "Word": "демон"}, {"Tags": ["Item"], "Genus": "m", "Word": "жгут"}, {"Tags": ["Item"], "Genus": "m", "Word": "платок"}, {"Tags": ["Item", "Creature"], "Genus": "f", "Word": "банка"}, {"Tags": ["Location"], "Genus": "f", "Word": "пустыня"}, {"Tags": ["Item", "Creature"], "Genus": "m", "Word": "шар"}, {"Tags": ["Creature"], "Genus": "m", "Word": "командир"}, {"Tags": ["Creature", "Item"], "Genus": "m", "Word": "капитан"}, {"Tags": ["Item", "Creature", "Location"], "Genus": "m", "Word": "вихрь"}, {"Tags": ["Item", "Creature"], "Genus": "m", "Word": "водоворот"}, {"Tags": ["Location", "Item"], "Genus": "f", "Word": "гроза"}, {"Tags": ["Item"], "Genus": "f", "Word": "загадка"}, {"Tags": ["Item", "Creature"], "Genus": "m", "Word": "снеговик"}, {"Tags": ["Creature"], "Genus": "m", "Word": "суккуб"}, {"Tags": ["Item", "Creature", "Location"], "Genus": "m", "Word": "уничтожитель"}, {"Tags": ["Item", "Location"], "Genus": "m", "Word": "погром"}, {"Tags": ["Item", "Creature"], "Genus": "f", "Word": "судьба"}, {"Tags": ["Creature"], "Genus": "m", "Word": "маг"}, {"Tags": ["Creature"], "Genus": "m", "Word": "некромант"}, {"Tags": ["Creature"], "Genus": "m", "Word": "рыцарь"}, {"Tags": ["Item"], "Genus": "m", "Word": "щит"}, {"Tags": ["Item"], "Genus": "m", "Word": "жезл"}, {"Tags": ["Item"], "Genus": "f", "Word": "палка"}, {"Tags": ["Item"], "Genus": "m", "Word": "посох"}, {"Tags": ["Item"], "Genus": "f", "Word": "коса"}, {"Tags": ["Creature"], "Genus": "m", "Word": "волк"}, {"Tags": ["Location"], "Genus": "m", "Word": "лес"}, {"Tags": ["Location"], "Genus": "m", "Word": "океан"}, {"Tags": ["Item"], "Genus": "m", "Word": "зов"}, {"Tags": ["Item"], "Genus": "f", "Word": "жалость"}, {"Tags": ["Item"], "Genus": "m", "Word": "укус"}, {"Tags": ["Item"], "Genus": "f", "Word": "веточка"}, {"Tags": ["Item", "Creature"], "Genus": "m", "Word": "клык"}, {"Tags": ["Item", "Creature"], "Genus": "f", "Word": "кость"}, {"Tags": ["Item"], "Genus": "f", "Word": "слеза"}, {"Tags": ["Item", "Location"], "Genus": "f", "Word": "сила"}, {"Tags": ["Item"], "Genus": "f", "Word": "перчатка"}, {"Tags": ["Item", "Location"], "Genus": "f", "Word": "бездна"}, {"Tags": ["Item", "Creature"], "Genus": "f", "Word": "катастрофа"}, {"Tags": ["Item", "Location"], "Genus": "f", "Word": "полость"}, {"Tags": ["Item", "Creature"], "Genus": "f", "Word": "дырка"}, {"Tags": ["Item"], "Genus": "m", "Word": "аспирин"}, {"Tags": ["Creature"], "Genus": "m", "Word": "лекарь"}, {"Tags": ["Creature"], "Genus": "m", "Word": "чародей"}, {"Tags": ["Creature"], "Genus": "f", "Word": "ведьма"}, {"Tags": ["Creature"], "Genus": "f", "Word": "колдунья"}, {"Tags": ["Item"], "Genus": "m", "Word": "распарыватель"}, {"Tags": ["Item"], "Genus": "m", "Word": "рассекатель"}, {"Tags": ["Item"], "Genus": "m", "Word": "кромсатель"}, {"Tags": ["Item"], "Genus": "m", "Word": "цареубийца"}, {"Tags": ["Item"], "Genus": "f", "Word": "шпора"}, {"Tags": ["Item"], "Genus": "f", "Word": "волна"}, {"Tags": ["Item"], "Genus": "m", "Word": "самострел"}, {"Tags": ["Item", "Location"], "Genus": "m", "Word": "раскол"}, {"Tags": ["Item", "Location"], "Genus": "f", "Word": "трещина"}, {"Tags": ["Item"], "Genus": "m", "Word": "язык"}, {"Tags": ["Item"], "Genus": "f", "Word": "муть"}, {"Tags": ["Item"], "Genus": "m", "Word": "мотив"}, {"Tags": ["Item"], "Genus": "f", "Word": "колотушка"}, {"Tags": ["Item", "Creature"], "Genus": "m", "Word": "мозг"}, {"Tags": ["Item", "Creature"], "Genus": "f", "Word": "балда"}, {"Tags": ["Item"], "Genus": "m", "Word": "палец"}, {"Tags": ["Item", "Creature"], "Genus": "f", "Word": "колючка"}, {"Tags": ["Creature"], "Genus": "m", "Word": "герой"}, {"Tags": ["Creature"], "Genus": "m", "Word": "хомячок"}, {"Tags": ["Creature"], "Genus": "f", "Word": "девственница"}, {"Tags": ["Creature"], "Genus": "f", "Word": "вредина"}, {"Tags": ["Item", "Location"], "Genus": "f", "Word": "влажность"}, {"Tags": ["Creature"], "Genus": "f", "Word": "куропатка"}, {"Tags": ["Creature"], "Genus": "m", "Word": "берсеркер"}, {"Tags": ["Creature"], "Genus": "m", "Word": "гоблин"}, {"Tags": ["Creature"], "Genus": "f", "Word": "чебурашка"}, {"Tags": ["Creature"], "Genus": "m", "Word": "джедай"}, {"Tags": ["Location"], "Genus": "f", "Word": "саванна"}, {"Tags": ["Location"], "Genus": "m", "Word": "космос"}, {"Tags": ["Item"], "Genus": "f", "Word": "опухоль"}, {"Tags": ["Item"], "Genus": "f", "Word": "свечка"}, {"Tags": ["Item"], "Genus": "m", "Word": "куст"}, {"Tags": ["Item", "Location"], "Genus": "f", "Word": "ось"}, {"Tags": ["Creature"], "Genus": "m", "Word": "наркоман"}, {"Tags": ["Creature", "Item"], "Genus": "f", "Word": "кружка"}, {"Tags": ["Creature"], "Genus": "f", "Word": "корова"}, {"Tags": ["Creature"], "Genus": "m", "Word": "кузнец"}, {"Tags": ["Item"], "Genus": "f", "Word": "майка"}, {"Tags": ["Creature"], "Genus": "f", "Word": "зайка"}, {"Tags": ["Creature"], "Genus": "m", "Word": "дельфинчик"}, {"Tags": ["Creature"], "Genus": "m", "Word": "ангелочек"}, {"Tags": ["Item"], "Genus": "m", "Word": "амулет"}, {"Tags": ["Item"], "Genus": "m", "Word": "кулон"}, {"Tags": ["Item"], "Genus": "m", "Word": "браслет"}, {"Tags": ["Item"], "Genus": "f", "Word": "варежка"}]}